<?xml version="1.0" encoding="UTF-8"?>
<generator_policy>
   <generator name="URIorUUID" type="any">
      <custom generatorClass="gr.forth.URIorUUID">
         <set-arg name="text"/>
      </custom>
   </generator>
   <generator name="URIwithTypeAndId" prefix="sirius" type="any">
      <pattern>/{type}/{id}</pattern>
   </generator>
   <generator name="URIwith2TypesAndId" prefix="sari" type="any">
      <pattern>{type1}/{type2}/{id}</pattern>
   </generator>
   <generator name="URIwithGndId" prefix="gnd" type="any">
      <pattern>{id}</pattern>
   </generator>
   <generator name="URIwithUlanId" prefix="ulan" type="any">
      <pattern>{id}</pattern>
   </generator>
   <generator name="URIwithWikidataId" prefix="wikidata" type="any">
      <pattern>{id}</pattern>
   </generator>
   <generator name="TypedLiteralGen" type="any">
      <custom generatorClass="gr.forth.TypedLiteralGenerator">
         <set-arg name="text"/>
      </custom>
   </generator>
   <generator name="ArtistURI" prefix="artist" type="any">
      <pattern>{type}/{id}</pattern>
   </generator>
   <generator name="CollectionURI" prefix="inst" type="any">
      <pattern>{type}/{id}</pattern>
   </generator>
   <generator name="DrawingSideURI" prefix="pref" type="any">
      <pattern>{side}/{id}</pattern>
   </generator>
   <generator name="DrawingVisualURI" prefix="pref" type="any">
      <pattern>{side}/{visual}/{id}</pattern>
   </generator>
   <generator name="Identifier" prefix="pref" type="any">
      <pattern>{type}/{id}/{identifier}</pattern>
   </generator>
   <generator name="DrawingSideIdentifier" prefix="pref" type="any">
      <pattern>{side}/{type}/{id}/{identifier}/</pattern>
   </generator>
   <generator name="IntermediateURI" prefix="pref" type="any">
      <pattern>{type}/{id}/{number}</pattern>
   </generator>
   <generator name="GenericURI" prefix="pref" type="any">
      <pattern>{type}/{id}</pattern>
   </generator>
   <generator name="GenericEditionURI" prefix="pref" type="any">
      <pattern>{year}/{type}/{id}</pattern>
   </generator>
   <generator name="LocalTermURI" prefix="pref" type="any">
      <pattern>{hierarchy}/{term}</pattern>
   </generator>
   <generator name="DrawingSideIntermediateURI" prefix="pref" type="any">
      <pattern>{side}/{type}/{id}/{number}</pattern>
   </generator>
   <generator name="DrawingSideIntermediateURI2" prefix="pref" type="any">
      <pattern>{side}/{type}/{id}</pattern>
   </generator>
   <generator name="valueRiskIDGen" prefix="sirius" type="any">
      <pattern>/risk-aspect/id/{id}</pattern>
   </generator>
   <generator name="risk-analysisID" prefix="sirius" type="any">
      <pattern>risk-analysis/id/{id}</pattern>
   </generator>
   <generator name="URIwithID" prefix="sirius" type="any">
      <pattern>/{id}</pattern>
   </generator>
   <generator name="site_ID" prefix="sirius" type="any">
      <pattern>/site/id/{id}</pattern>
   </generator>
   <generator name="ScaleAScore" prefix="sirius" type="any">
      <pattern>/scale_a_score/{site_id}/{risk_id}/{score}</pattern>
   </generator>
   <generator name="ScaleADescription" prefix="sirius" type="any">
      <pattern>/scale_a_description/{site_id}/{risk_id}/{description}</pattern>
   </generator>
   <generator name="riskID" prefix="sirius" type="any">
      <pattern>/risk-id/{id}</pattern>
   </generator>
   <generator name="risk-event" prefix="sirius" type="any">
      <pattern>/risk-event/{event}</pattern>
   </generator>
   <generator name="type_score" prefix="sirius" type="any">
      <pattern>/type/{type}</pattern>
   </generator>
   <generator name="ScaleBScore" prefix="sirius" type="any">
      <pattern>/scale_b_score/{site_id}/{risk_id}/{score}</pattern>
   </generator>
   <generator name="ScaleCScore" prefix="sirius" type="any">
      <pattern>/scale_c_score/{site_id}/{risk_id}/{score}</pattern>
   </generator>
   <generator name="ScaleBDescription" prefix="sirius" type="any">
      <pattern>/scale_b_description/{site_id}/{risk_id}/{description}</pattern>
   </generator>
   <generator name="ScaleCDescription" prefix="sirius" type="any">
      <pattern>/scale_c_description/{site_id}/{risk_id}/{description}</pattern>
   </generator>
   <generator name="magnitudeScore" prefix="sirius" type="any">
      <pattern>/magnitude_score/{site_id}/{risk_id}/{score}</pattern>
   </generator>
   <generator name="uncertainty" prefix="sirius" type="any">
      <pattern>/uncertainty/{site_id}/{risk_id}/{score}</pattern>
   </generator>
   <generator name="URIwithType" prefix="sirius" type="any">
      <pattern>/{type}</pattern>
   </generator>
   <generator name="URIwithAgentandID" prefix="sirius" type="any">
      <pattern>/agent/{type}/{id}</pattern>
   </generator>
</generator_policy>
